rlPyCairo/INSTALL.txt
rlPyCairo/LICENSE.txt
rlPyCairo/README.txt
rlPyCairo/__init__.py
rlPyCairo/gstate.py
rlPyCairo/pil2pict.py
rlPyCairo-0.2.0.dist-info/METADATA
rlPyCairo-0.2.0.dist-info/WHEEL
rlPyCairo-0.2.0.dist-info/top_level.txt
rlPyCairo-0.2.0.dist-info/RECORD
